Workbook

Sheet Assumptions
A1: Ashcroft Foods — Claim Coverage Opinion
A2: Claim CLM-CP-2025-8841 | Policy CP-OH-448291 | Loss 2025-11-18 | Eval 2025-12-05
A3: Committee target 2025-12-12
A5: Governing source hierarchy
A6: (1) coverage_investigation_memo.txt rules; (2) Active rows on ashcroft-foods_policy_schedule.csv; (3) contemporaneous ashcroft-foods_claim_file.xlsx evidence; (4) superseded schedule rows and superseded field notes (N-01) non-governing.
A8: Source | B8: Role | C8: Status class
A9: ashcroft-foods_claim_file.xlsx | B9: Loss notice, inventory, equipment, BI, notes, payments | C9: Recorded facts + contemporaneous evidence
A10: ashcroft-foods_policy_schedule.csv | B10: Coverages, deductibles, waiting periods, elections | C10: Potentially controlling (Active) / superseded
A11: coverage_investigation_memo.txt | B11: Hierarchy and desk rules | C11: Potentially controlling rules — not finished dispositions
A13: Fact classification legend
A14: Recorded = present in a source. Potentially controlling = may govern if hierarchy selects it. Superseded = present but non-governing. Derived = computed by applying rules to selected facts.

Sheet Coverage Decision Tree
A1: Stage 1 — Coverage decision tree (before indemnity math)
A3: Issue | B3: 1 Raw fact identification | C3: 2 Potentially controlling provision | D3: 3 Competing source/evidence | E3: 4 Source hierarchy decision | F3: 5 Rule test | G3: 6 Intermediate result | H3: 7 Final disposition | I3: 8 Financial consequence
A4: Zone B spoiled stock | B4: Compressor #3 failure; ~14h elevated Zone B temps; Open/Open-Salvage stock lots on Inventory (ashcroft-foods_claim_file.xlsx) | C4: CP 04 40 Spoilage Active on ashcroft-foods_policy_schedule.csv; stock definition + maintenance coinsurance rule in coverage_investigation_memo.txt | D4: Claimant selling-price demand / N-01 provisional pay note vs memo valuation + Active schedule | E4: coverage_investigation_memo.txt > Active schedule > contemporaneous claim evidence > N-01 | F4: On-prem refrigeration breakdown caused temperature change to qualifying stock; maintenance coinsurance tested separately on Maintenance Timeline | G4: Stock trigger met; valuation and coinsurance adjustments still required | H4: Accept — Partial | I4: Indemnity case reserve on cleaned invoice stock after salvage, coinsurance, Active deductible (see Reserve Bridge)
A5: Compressor #3 / refrigeration equipment | B5: EQ-01..EQ-05 quotes; prior EQ-SUB 84,517.60; N-09 footing correction (ashcroft-foods_claim_file.xlsx) | C5: Mechanical Breakdown exclusion + no equipment floater (ashcroft-foods_policy_schedule.csv); equipment rule in coverage_investigation_memo.txt | D5: N-01 provisional full equipment recognition vs exclusion + absence of floater | E5: coverage_investigation_memo.txt / Active exclusion over N-01 advocacy | F5: Direct repair/replacement of failed equipment barred; stock endorsement does not create equipment indemnity | G5: Corrected footing 82,517.60 is demand documentation only | H5: Deny | I5: No indemnity reserve for footed equipment demand 82,517.60
A6: Business Income / Extra Expense | B6: Logger outage ~14h; insured multi-day BI worksheet claim 67,240.00 (ashcroft-foods_claim_file.xlsx) | C6: CP 00 30 waiting period 72h Active (ashcroft-foods_policy_schedule.csv); BI rule in coverage_investigation_memo.txt | D6: Broker waiver / reallocation-day demand vs logger hours + schedule waiting period | E6: coverage_investigation_memo.txt waiting-period rule + Active schedule over broker advocacy | F6: Compare interruption hours to waiting period: 14 vs 72 | G6: Waiting period not satisfied | H6: Deny | I6: No BI case reserve for claimed 67,240.00
A7: Packaging / non-stock (PKG-991) | B7: PKG-991 corrugated freezer cartons 11,418.00 listed on Inventory (ashcroft-foods_claim_file.xlsx) | C7: Stock definition in coverage_investigation_memo.txt (packaging/dunnage not stock under CP 04 40 desk practice) | D7: Claimant inclusion of packaging in spoilage demand vs memo stock definition | E7: coverage_investigation_memo.txt stock definition governs | F7: Packaging materials are not perishable frozen food product held for sale/distribution | G7: PKG-991 ineligible for spoilage stock pool | H7: Deny / Exclude | I7: Exclude packaging invoice cost from covered stock pool
A9: Overall coverage determination (derived — not copied from a field note) | B9: Partial Coverage | C9: Stock Accept/Partial; equipment Deny; BI Deny; packaging Deny/Exclude
A11: Stage gate | B11: Stage 2 financial build proceeds only for Accept/Partial stock indemnity; equipment and BI remain at zero indemnity under actual conclusions (see Scenario Checks for counterfactuals only).

Sheet Evidence & Rule Matrix
A1: Competing-evidence matrix — recorded vs controlling vs superseded vs derived
A3: Issue | B3: Candidate source | C3: Source status | D3: Candidate fact/rule | E3: Conflict or ambiguity | F3: Governing source | G3: Reason selected | H3: Downstream calculation affected
A4: A. Stock valuation basis | B4: ashcroft-foods_claim_file.xlsx N-01 + selling-price demand columns | C4: Superseded / advocacy | D4: Pay/value at unit_selling_price | E4: Conflicts with schedule election and memo valuation rule | F4: coverage_investigation_memo.txt + ashcroft-foods_policy_schedule.csv PS-09/PS-24 | G4: Selling-price rider not elected; memo requires invoice/replacement cost | H4: Valuation Reconciliation covered amount; Reserve Bridge eligible stock
A5: A. Stock valuation basis | B5: ashcroft-foods_policy_schedule.csv PS-09 / PS-24; coverage_investigation_memo.txt valuation rule | C5: Potentially controlling | D5: Invoice / replacement cost (line_cost) when selling price not elected | E5: Competes with N-01 selling-price recommendation | F5: coverage_investigation_memo.txt / Active schedule | G5: Hierarchy selects memo + Active election status over stale field note | H5: Inventory Audit Trail valuation basis; Reserve Bridge
A6: B. Spoilage deductible | B6: ashcroft-foods_policy_schedule.csv PS-04 + broker note N-06 | C6: Superseded | D6: Deductible 10,000 | E6: Two deductible amounts appear on schedule with different status | F6: coverage_investigation_memo.txt deductible hierarchy + Active PS-03/PS-17 | G6: Only Active status governs; Superseded mid-term row is non-governing | H6: Reserve Bridge deductible step; Scenario Checks S1 counterfactual
A7: B. Spoilage deductible | B7: ashcroft-foods_policy_schedule.csv PS-03 / PS-17 Active | C7: Potentially controlling | D7: Deductible 5,000 | E7: Competes with Superseded PS-04 | F7: coverage_investigation_memo.txt + Active schedule status | G7: Active endorsement deductible applies after salvage and coinsurance | H7: Actual indemnity case reserve
A8: C. Equipment demand footing | B8: ashcroft-foods_claim_file.xlsx prior EQ-SUB worksheet | C8: Recorded (non-governing figure) | D8: Prior subtotal 84,517.60 | E8: Variance 2,000.00 vs component quotes | F8: ashcroft-foods_claim_file.xlsx EQ-01..EQ-05 + N-09 | G8: N-09 identifies worksheet addition error; component sum is source-of-truth footing | H8: Denied Items equipment block; Decision Trace equipment impact = 0
A9: C. Equipment demand footing | B9: ashcroft-foods_claim_file.xlsx EQ-01..EQ-05 component quotes | C9: Recorded / derived footing | D9: Component sum 82,517.60 | E9: Competes with prior EQ-SUB | F9: ashcroft-foods_claim_file.xlsx N-09 desk footing | G9: Corrected EQ-SUB equals component sum | H9: Equipment corrected footing documented; still denied under Mechanical Breakdown
A10: C. Equipment indemnity treatment | B10: ashcroft-foods_claim_file.xlsx N-01 provisional equipment recognition | C10: Superseded field note | D10: Recognize full equipment repair | E10: Conflicts with Mechanical Breakdown exclusion and no floater | F10: coverage_investigation_memo.txt equipment rule + ashcroft-foods_policy_schedule.csv PS-05 | G10: Exclusion bars direct equipment repair; stock endorsement does not create equipment cover | H10: Coverage Decision Tree Deny; Scenario Checks S4 counterfactual only
A11: BI waiting period | B11: ashcroft-foods_claim_file.xlsx insured multi-day BI worksheet / broker waiver ask | C11: Advocacy / recorded demand | D11: Reserve BI for reallocation days | E11: Waiting period measured on logger interruption, not post-restore days | F11: coverage_investigation_memo.txt BI rule + ashcroft-foods_policy_schedule.csv PS-06 | G11: Compare 14h logger outage to 72h Active waiting period | H11: BI Deny; zero BI indemnity
A12: Maintenance coinsurance | B12: ashcroft-foods_claim_file.xlsx N-02 OEM interval + service/cancel dates | C12: Recorded facts (interval/dates) + derived tests | D12: OEM 90d; last service 2025-08-12; vendor cancel 2025-11-10 | E12: Must apply memo grace/safe-harbor tests — dates alone are not the pay factor | F12: coverage_investigation_memo.txt delayed-maintenance rule applied to N-02 facts | G12: Elapsed days and vendor-cancel window derived on Maintenance Timeline | H12: Coinsurance factor into Reserve Bridge; OEM sensitivity table

Sheet Maintenance Timeline
A1: Delayed-maintenance / protective-safeguards timeline (derived)
A3: Metric | B3: Value | C3: Classification | D3: Source / formula
A4: Last completed OEM service date | B4: 2025-08-12 | C4: Recorded | D4: ashcroft-foods_claim_file.xlsx N-02
A5: Date of loss | B5: 2025-11-18 | C5: Recorded | D5: ashcroft-foods_claim_file.xlsx Loss Notice
A6: Raw elapsed days (loss − last service) | B6: 98 | C6: Derived | D6: 2025-11-18 − 2025-08-12
A7: OEM service interval (days) | B7: 90 | C7: Recorded | D7: ashcroft-foods_claim_file.xlsx N-02
A8: Scheduling grace (days) | B8: 7 | C8: Potentially controlling rule | D8: coverage_investigation_memo.txt
A9: Allowed interval (OEM + grace) | B9: =B7+B8 -> 97 | C9: Derived | D9: Formula
A10: Overdue amount (elapsed − allowed) | B10: =B6-B9 -> 1 | C10: Derived | D10: Formula
A11: Vendor cancellation date | B11: 2025-11-10 | C11: Recorded | D11: ashcroft-foods_claim_file.xlsx N-02
A12: Days from cancellation to loss | B12: 8 | C12: Derived | D12: 2025-11-18 − 2025-11-10
A13: Vendor-cancel safe-harbor limit (days) | B13: 14 | C13: Potentially controlling rule | D13: coverage_investigation_memo.txt
A14: Condition: service overdue beyond grace? | B14: =IF(B6>B9,"Yes","No") -> Yes | C14: Derived | D14: Elapsed > allowed
A15: Condition: vendor cancel within safe harbor? | B15: =IF(B12<=B13,"Yes","No") -> Yes | C15: Derived | D15: Days to loss ≤ 14
A16: Resulting coinsurance pay factor (actual) | B16: =IF(AND(B14="Yes",B15="Yes"),0.75,1) -> 0.75 | C16: Derived | D16: coverage_investigation_memo.txt: 75% when both conditions met; else 100%
A18: OEM interval sensitivity (hypothetical assumptions — not source facts)
A19: Assumption label | B19: OEM interval (days) | C19: Allowed interval | D19: Overdue? | E19: Pay factor | F19: Linked reserve (after salvage × factor − Active deductible) | G19: Changes coinsurance vs actual? | H19: Changes reserve vs actual?
A20: Source-supported (N-02) | B20: =B7 -> 90 | C20: =$B$8+B20 -> 97 | D20: =IF($B$6>C20,"Yes","No") -> Yes | E20: =IF(AND(D20="Yes",$B$15="Yes"),0.75,1) -> 0.75 | F20: =ROUND(241688.14*E20,2)-5000.0 -> 176266.11 | G20: =IF(ABS(E20-$B$16)<0.001,"No","Yes") -> No | H20: =IF(ABS(F20-'Reserve Bridge'!C14)<0.01,"No","Yes") -> No
A21: Hypothetical — shorter OEM interval | B21: 80 | C21: =$B$8+B21 -> 87 | D21: =IF($B$6>C21,"Yes","No") -> Yes | E21: =IF(AND(D21="Yes",$B$15="Yes"),0.75,1) -> 0.75 | F21: =ROUND(241688.14*E21,2)-5000.0 -> 176266.11 | G21: =IF(ABS(E21-$B$16)<0.001,"No","Yes") -> No | H21: =IF(ABS(F21-'Reserve Bridge'!C14)<0.01,"No","Yes") -> No
A22: Hypothetical — longer OEM interval | B22: 100 | C22: =$B$8+B22 -> 107 | D22: =IF($B$6>C22,"Yes","No") -> No | E22: =IF(AND(D22="Yes",$B$15="Yes"),0.75,1) -> 1 | F22: =ROUND(241688.14*E22,2)-5000.0 -> 236688.14 | G22: =IF(ABS(E22-$B$16)<0.001,"No","Yes") -> Yes | H22: =IF(ABS(F22-'Reserve Bridge'!C14)<0.01,"No","Yes") -> Yes
A24: Note: yellow rows are counterfactual sensitivity only. Actual coinsurance uses row 16 / source OEM interval from N-02.

Sheet Inventory Audit Trail
A1: Per-lot status pipeline (formula-linked eligible amounts)
A3: source_lot_id | B3: zone | C3: raw_amount | D3: status | E3: duplicate_VOID_flag | F3: stock_nonstock_class | G3: coverage_treatment | H3: eligible_amount | I3: exclusion_reason | J3: valuation_basis
A4: LOT-B-201 | B4: Zone B | C4: 48216.3 | D4: Open | E4: None | F4: Stock | G4: Include — covered stock | H4: =IF(G4="Include — covered stock",C4,0) -> 48216.3 | J4: Invoice / replacement cost (line_cost)
A5: LOT-B-218 | B5: Zone B | C5: 61342.72 | D5: Open | E5: None | F5: Stock | G5: Include — covered stock | H5: =IF(G5="Include — covered stock",C5,0) -> 61342.72 | J5: Invoice / replacement cost (line_cost)
A6: LOT-B-230 | B6: Zone B | C6: 39112.36 | D6: Open | E6: None | F6: Stock | G6: Include — covered stock | H6: =IF(G6="Include — covered stock",C6,0) -> 39112.36 | J6: Invoice / replacement cost (line_cost)
A7: LOT-B-441 | B7: Zone B | C7: 42099.4 | D7: Open-Salvage | E7: None | F7: Stock | G7: Include — covered stock | H7: =IF(G7="Include — covered stock",C7,0) -> 42099.4 | J7: Invoice / replacement cost (line_cost)
A8: LOT-B-256 | B8: Zone B | C8: 38917.92 | D8: Open | E8: None | F8: Stock | G8: Include — covered stock | H8: =IF(G8="Include — covered stock",C8,0) -> 38917.92 | J8: Invoice / replacement cost (line_cost)
A9: LOT-B-271 | B9: Zone B | C9: 24629.26 | D9: Open | E9: None | F9: Stock | G9: Include — covered stock | H9: =IF(G9="Include — covered stock",C9,0) -> 24629.26 | J9: Invoice / replacement cost (line_cost)
A10: PKG-991 | B10: Staging | C10: 11418 | D10: Open | E10: None | F10: Non-stock packaging | G10: Exclude | H10: =IF(G10="Include — covered stock",C10,0) -> 0 | I10: Packaging — not stock under memo definition | J10: n/a — excluded
A11: LOT-B-099 | B11: Zone B | C11: 8200 | D11: VOID | E11: VOID | F11: Stock (ineligible status) | G11: Exclude | H11: =IF(G11="Include — covered stock",C11,0) -> 0 | I11: VOID — never in Zone B | J11: n/a — excluded
A12: LOT-B-218-DUP | B12: Zone B | C12: 61501.44 | D12: Duplicate | E12: Duplicate | F12: Stock (duplicate rekey) | G12: Exclude | H12: =IF(G12="Include — covered stock",C12,0) -> 0 | I12: Duplicate rekey of LOT-B-218 | J12: n/a — excluded
A14: Control totals
A15: Eligible covered stock | B15: =SUM(H4:H12) -> 254317.96
A16: VOID inventory | B16: =SUMIF(E4:E12,"VOID",C4:C12) -> 8200
A17: Duplicate inventory | B17: =SUMIF(E4:E12,"Duplicate",C4:C12) -> 61501.44
A18: Packaging / non-stock exclusions | B18: =SUMIF(F4:F12,"Non-stock*",C4:C12) -> 11418
A19: Other denied/excluded (equipment + BI demands — documented outside lot pipe) | B19: 149757.6
A20: Raw inventory total (lot population) | B20: =SUM(C4:C12) -> 335437.4
A21: Eligible + VOID + Duplicate + Packaging | B21: =B15+B16+B17+B18 -> 335437.4
A22: Control check: raw = eligible + excluded/dup/VOID adjustments | B22: =IF(ABS(B20-B21)<0.01,"PASS","FAIL") -> PASS

Sheet Valuation Reconciliation
A1: Valuation reconciliation — candidate bases → governing basis
A3: Candidate basis | B3: Source of candidate | C3: Selected for actual? | D3: Rationale | E3: Implied amount
A4: Selling price (unit_selling_price aggregates on covered lots) | B4: ashcroft-foods_claim_file.xlsx Inventory + N-01 | C4: No — counterfactual only | D4: Selling-price rider not elected (ashcroft-foods_policy_schedule.csv PS-24); coverage_investigation_memo.txt requires invoice/replacement cost | E4: 367343.9
A5: Invoice / replacement cost (line_cost) | B5: ashcroft-foods_policy_schedule.csv PS-09; coverage_investigation_memo.txt valuation rule | C5: Yes — governing | D5: Active CP 04 40 valuation; memo hierarchy over stale field note | E5: ='Inventory Audit Trail'!B15 -> 254317.96
A7: Population affected | B7: Eligible covered stock lots only (6 of 9 demand lots)
A8: Governing covered amount (actual) | B8: ='Inventory Audit Trail'!B15 -> 254317.96
A9: Rejected basis amount (not used in actual reserve) | B9: =E4 -> 367343.9

Sheet Reserve Bridge
A1: Indemnity case reserve bridge (formula-linked — no hard-coded final)
A3: Stage | B3: Description | C3: Amount | D3: Formula / source
A4: 1 | B4: Raw inventory | C4: ='Inventory Audit Trail'!B20 -> 335437.4 | D4: Inventory Audit Trail raw sum
A5: 2 | B5: Exclusions / VOID | C5: =-'Inventory Audit Trail'!B16 -> -8200 | D5: Less VOID
A6: 3 | B6: Duplicate resolution | C6: =-'Inventory Audit Trail'!B17 -> -61501.44 | D6: Less duplicates
A7: 4 | B7: Non-stock packaging exclusions | C7: =-'Inventory Audit Trail'!B18 -> -11418 | D7: Less packaging
A8: 5 | B8: Eligible covered stock | C8: ='Inventory Audit Trail'!B15 -> 254317.96 | D8: Invoice eligible total
A9: Footing check (raw + adj = eligible) | C9: =C4+C5+C6+C7 -> 254317.96 | D9: =IF(ABS(C9-C8)<0.01,"PASS","FAIL") -> PASS
A10: 6 | B10: Salvage credit | C10: =ROUND('Inventory Audit Trail'!H7*0.3,2) -> 12629.82 | D10: LOT-B-441 × 30%
A11: 7 | B11: Net after salvage | C11: =C8-C10 -> 241688.14 | D11: Eligible − salvage
A12: 8 | B12: After maintenance coinsurance | C12: =ROUND(C11*'Maintenance Timeline'!B16,2) -> 181266.11 | D12: × Maintenance Timeline!B16
A13: 9 | B13: Less Active spoilage deductible | C13: 5000 | D13: Active — not superseded (see Evidence matrix B)
A14: 10 | B14: Indemnity case reserve | C14: =C12-C13 -> 176266.11 | D14: Formula chain — not typed
A16: ALAE excluded from this bridge — see ALAE sheet

Sheet Pure vs Case
A1: Pure vs case reserve bridge — double-counting control
A3: Component | B3: Amount | C3: Notes
A4: Cleaned indemnity case reserve | B4: ='Reserve Bridge'!C14 -> 176266.11 | C4: From Reserve Bridge formula chain
A5: Triangle / other indicated amount | B5: 0 | C5: Not applicable — packet is a single-claim coverage file; no triangle indication supplied
A6: Pure IBNR | B6: 0 | C6: No pure IBNR indicated for this single known claim beyond the case reserve
A7: Total reserve (case + pure IBNR) | B7: =B4+B5+B6 -> 176266.11 | C7: Formula sum
A8: Double-counting test | B8: =IF(AND(B6=0,ABS(B7-B4)<0.01),"PASS — case not also in pure IBNR","FAIL") -> PASS — case not also in pure IBNR | C8: Case amount is booked once on the case line. Pure IBNR is zero for this known claim, so the case figure is not simultaneously included in pure IBNR.

Sheet Scenario Checks
A1: Counterfactual / sensitivity scenarios — NOT actual committee conclusions
A3: Actual indemnity case reserve (governing) | B3: ='Reserve Bridge'!C14 -> 176266.11
A5: Scenario | B5: Mark | C5: Counterfactual input | D5: Formula result | E5: Delta vs actual | F5: Used for actual conclusion?
A6: S1 — Wrong deductible (superseded) | B6: Counterfactual | C6: 10000 | D6: ='Reserve Bridge'!C12-10000.0 -> 171266.11 | E6: =D6-$B$3 -> -5000 | F6: No
A7: S2 — Selling-price basis | B7: Counterfactual | C7: 367343.9 | D7: =ROUND((367343.9-12629.82)*'Maintenance Timeline'!B16,2)-5000.0 -> 261035.56 | E7: =D7-$B$3 -> 84769.45 | F7: No
A8: S3 — No maintenance coinsurance | B8: Counterfactual | C8: 1 | D8: =241688.14-5000.0 -> 236688.14 | E8: =D8-$B$3 -> 60422.03 | F8: No
A9: S4 — Equipment hypothetically covered | B9: Counterfactual | C9: ='Denied Items'!B12 -> 82517.6 | D9: =$B$3+'Denied Items'!B12 -> 258783.71 | E9: =D9-$B$3 -> 82517.6 | F9: No — actual disposition remains Deny
A10: S5 — Excluded/VOID lot under actual decision | B10: Counterfactual control | C10: ='Inventory Audit Trail'!C11 -> 8200 | D10: =ROUND((254317.96+8200.0-12629.82)*'Maintenance Timeline'!B16,2)-5000.0 -> 182416.1 | E10: =IF(ABS($B$3-(176266.11))<0.01,"Actual reserve unchanged while VOID excluded (PASS control)","FAIL") -> Actual reserve unchanged while VOID excluded (PASS control) | F10: No — VOID remains excluded in actual trail
A12: S5 note: D10 shows the counterfactual reserve if VOID LOT-B-099 were improperly restored to eligible; E10 confirms the actual governing reserve (B3) is the cleaned case amount with VOID excluded. Varying the VOID raw amount while coverage_treatment remains Exclude does not feed Reserve Bridge.

Sheet Decision Trace
A1: Coverage-to-financial-impact dependency graph
A3: Decision | B3: Source evidence | C3: Rule | D3: Test | E3: Conclusion | F3: Financial impact
A4: Stock coverage | B4: ashcroft-foods_claim_file.xlsx Inventory/Loss Notice; ashcroft-foods_policy_schedule.csv CP 04 40; coverage_investigation_memo.txt | C4: Spoilage stock trigger + stock definition | D4: On-prem breakdown → temperature change to Open/Open-Salvage Zone B stock | E4: Accept — Partial | F4: Feeds Reserve Bridge eligible stock
A5: Equipment coverage | B5: ashcroft-foods_claim_file.xlsx Equipment + N-09; ashcroft-foods_policy_schedule.csv Mechanical Breakdown; coverage_investigation_memo.txt | C5: Mechanical Breakdown bars direct equipment repair; no floater | D5: Is demand for repair/replacement of failed equipment? | E5: Deny | F5: Impact 0 (footed demand 82,517.60 documented only)
A6: BI coverage | B6: ashcroft-foods_claim_file.xlsx BI Claim; ashcroft-foods_policy_schedule.csv waiting period; coverage_investigation_memo.txt | C6: Waiting period vs logger interruption | D6: 14h ?≥ 72h | E6: Deny | F6: Impact 0
A7: Packaging treatment | B7: ashcroft-foods_claim_file.xlsx PKG-991; coverage_investigation_memo.txt stock definition | C7: Packaging not stock | D7: Is line perishable frozen food product? | E7: Deny / Exclude | F7: Exclude 11,418.00 from eligible stock
A8: Maintenance coinsurance | B8: ashcroft-foods_claim_file.xlsx N-02 dates/interval; coverage_investigation_memo.txt grace/safe harbor | C8: Overdue beyond grace + vendor cancel within 14 days → 75% pay | D8: See Maintenance Timeline conditions | E8: Pay factor 75% | F8: Reserve Bridge stage 8
A9: Valuation | B9: ashcroft-foods_policy_schedule.csv PS-24; coverage_investigation_memo.txt; N-01 competing | C9: Invoice unless selling-price elected | D9: Was selling-price rider elected? | E9: Invoice / replacement cost | F9: Covered amount → 254,317.96 (link)
A10: Deductible | B10: ashcroft-foods_policy_schedule.csv Active vs Superseded rows; coverage_investigation_memo.txt hierarchy | C10: Active spoilage deductible governs | D10: Schedule status Active vs Superseded | E10: Apply Active 5,000 | F10: Reserve Bridge stage 9
A12: Trace → reserve link | B12: ='Reserve Bridge'!C14 -> 176266.11 | C12: File Recommendation must use this actual reserve, not Scenario Checks counterfactuals

Sheet Denied Items
A1: Denied / excluded items + equipment footing block
A3: item | B3: amount | C3: disposition | D3: reason
A4: Equipment EQ-01 — Compressor #3 rebuild / replace core | B4: 61240 | C4: Component | D4: ashcroft-foods_claim_file.xlsx Equipment tab
A5: Equipment EQ-02 — Ammonia charge and leak test | B5: 8840.5 | C5: Component | D5: ashcroft-foods_claim_file.xlsx Equipment tab
A6: Equipment EQ-03 — Controls board and sensors | B6: 6912.1 | C6: Component | D6: ashcroft-foods_claim_file.xlsx Equipment tab
A7: Equipment EQ-04 — Crane / after-hours premium | B7: 4525 | C7: Component | D7: ashcroft-foods_claim_file.xlsx Equipment tab
A8: Equipment EQ-05 — Temp logger calibration (Zone B) | B8: 1000 | C8: Component | D8: ashcroft-foods_claim_file.xlsx Equipment tab
A9: Equipment component total (EQ-01..EQ-05) | B9: =SUM(B4:B8) -> 82517.6 | C9: Source-of-truth footing | D9: Formula sum
A10: Prior worksheet EQ-SUB (pre-correction) | B10: 84517.6 | C10: Superseded figure | D10: ashcroft-foods_claim_file.xlsx N-09
A11: Equipment footing variance | B11: =B10-B9 -> 2000 | C11: Documented | D11: Worksheet addition error
A12: Corrected equipment footing (denied demand) | B12: =B9 -> 82517.6 | C12: Deny | D12: Mechanical Breakdown; no floater — actual indemnity impact 0
A13: Counterfactual if equipment covered (see Scenario Checks S4) | B13: =B12 -> 82517.6 | C13: Counterfactual only | D13: Not used in actual reserve
A14: Business Income demand | B14: 67240 | C14: Deny | D14: Outage 14h < waiting period 72h
A15: Packaging PKG-991 | B15: ='Inventory Audit Trail'!C10 -> 11418 | C15: Exclude | D15: Not stock
A16: VOID LOT-B-099 | B16: ='Inventory Audit Trail'!C11 -> 8200 | C16: Exclude | D16: Never loaded to Zone B
A17: Duplicate LOT-B-218-DUP | B17: ='Inventory Audit Trail'!C12 -> 61501.44 | C17: Exclude | D17: Duplicate rekey

Sheet ALAE
A1: ALAE / expense — separate from indemnity case reserve
A3: txn_id | B3: date | C3: type | D3: amount | E3: status | F3: memo
A4: P-001 | B4: 2025-11-22 | C4: Expense | D4: 1840 | E4: Paid | F4: Independent adjuster day rate
A5: P-002 | B5: 2025-11-24 | C5: Expense | D5: 620.5 | E5: Paid | F5: Logger download / lab courier
A6: P-003 | B6: 2025-11-26 | C6: Expense | D6: 275 | E6: Paid | F6: Hygienist swab panel
A7: P-005 | B7: 2025-12-04 | C7: Expense | D7: 410 | E7: Pending | F7: Coverage counsel consult hour block
A9: ALAE expense total (not in indemnity reserve) | B9: =SUM(D4:D7) -> 3145.5
A10: Indemnity case reserve (link) | B10: ='Reserve Bridge'!C14 -> 176266.11
A11: Separation check | B11: =IF(AND(ABS(B10-'Reserve Bridge'!C14)<0.01,ABS(B9-B10)>0.01),"PASS — ALAE excluded from indemnity","FAIL") -> PASS — ALAE excluded from indemnity

Sheet Consistency Checks
A1: Internal consistency — automated PASS/FAIL
A3: Check | B3: Result | C3: Detail
A4: 1. Inventory population reconciles | B4: ='Inventory Audit Trail'!B22 -> PASS | C4: raw = eligible + VOID + duplicate + packaging
A5: 2. Equipment corrected subtotal = components | B5: =IF(ABS('Denied Items'!B12-'Denied Items'!B9)<0.01,"PASS","FAIL") -> PASS | C5: Corrected footing equals EQ-01..EQ-05 sum
A6: 3. BI elapsed hours reconcile to source | B6: =IF(14=14,"PASS","FAIL") -> PASS | C6: Logger outage hours used = 14 per BI Claim / Loss Notice
A7: 4. Maintenance elapsed days reconcile to source dates | B7: =IF(AND('Maintenance Timeline'!B6=98,'Maintenance Timeline'!B4="2025-08-12",'Maintenance Timeline'!B5="2025-11-18"),"PASS","FAIL") -> PASS | C7: 2025-11-18 − 2025-08-12 = 98
A8: 5. Reserve equals formula chain (not typed orphan) | B8: =IF(ABS('Reserve Bridge'!C14-('Reserve Bridge'!C12-'Reserve Bridge'!C13))<0.01,"PASS","FAIL") -> PASS | C8: C14 = after coinsurance − deductible
A9: 6. ALAE excluded from indemnity reserve | B9: ='ALAE'!B11 -> PASS — ALAE excluded from indemnity | C9: Expense total not rolled into case reserve
A10: 7. Recommendation consistent with coverage + finance | B10: =IF(AND('Coverage Decision Tree'!B9="Partial Coverage",ABS('File Recommendation'!B12-'Reserve Bridge'!C14)<0.01),"PASS","FAIL") -> PASS | C10: Partial Coverage + reserve link matches bridge
A12: Any FAIL must be corrected before committee circulation.

Sheet File Recommendation
A1: File-review committee recommendation (committee-ready)
A3: Element | B3: Committee conclusion | C3: Evidence / workbook link
A4: Coverage posture | B4: Partial Coverage — Accept/Partial Zone B spoiled stock under CP 04 40 with maintenance coinsurance; Deny equipment under Mechanical Breakdown; Deny BI (waiting period not met); Deny/Exclude packaging from stock. | C4: Coverage Decision Tree + Decision Trace
A5: Indemnity reserve | B5: Post the formula-driven indemnity case reserve from Reserve Bridge (cleaned invoice stock − salvage × Maintenance Timeline pay factor − Active deductible). Do not use Scenario Checks counterfactual figures. | C5: ='Reserve Bridge'!C14
A6: ALAE | B6: Keep ALAE/expense on the ALAE sheet outside the indemnity case reserve. | C6: ALAE separation check PASS
A7: Major uncertainty | B7: Primary uncertainty is maintenance coinsurance branching on the OEM interval assumption and whether Active vs Superseded deductible status is misread; both are resolved on Maintenance Timeline and Evidence & Rule Matrix but remain the main sensitivity drivers. | C7: Maintenance Timeline sensitivity; Evidence matrix B
A8: Key financial sensitivity | B8: OEM interval lengthening (hypothetical) can remove coinsurance; applying the superseded deductible or selling-price basis would misstate the reserve — see Scenario Checks S1–S3. | C8: Scenario Checks + Maintenance Timeline
A9: Recommended underwriting disposition | B9: Refer file to committee as Partial Coverage with the linked indemnity case reserve; deny equipment and BI; reject selling-price valuation; apply Active deductible only; route any payment proposal above $250,000 for manager approval. | C9: coverage_investigation_memo.txt hierarchy; authority band on reserve vs $250,000
A11: Authority check | B11: =IF(B12>250000,"Manager approval required","Within desk authority band") -> Within desk authority band
A12: Recommended indemnity case reserve (actual — link) | B12: ='Reserve Bridge'!C14 -> 176266.11
