Workbook

Sheet Cover
A1: Haverford Process Equipment LLC — Month-end GL flux close pack
A3: Period | B3: 2026-08
A4: Soft-close target | B4: 2026-09-05
A5: Governing policy | B5: flux_threshold_and_aje_memo.txt
A6: TB source | B6: haverford-process-equipment_trial_balance.xlsx
A7: Support source | B7: haverford-process-equipment_support_schedules.csv
A8: Close readiness | B8: Ready with AJEs
A9: Hierarchy | B9: flux_threshold_and_aje_memo.txt governs over Plant_Notes clean-close language
A11: Prepared for corporate accounting soft close. Proposed AJEs must post before books are labeled Ready. Warranty AJE uses W-04 governing support; the $6,000 detail-roll vs W-04 gap is an open source exception.

Sheet Flux_Workpaper
A1: Material flux investigation — 2026-08 vs prior
A3: Account | B3: Name | C3: Type | D3: July | E3: August | F3: Flux | G3: Flux_Pct_of_July | H3: Threshold_Hit | I3: Explanation | J3: Support_Ref
A4: 1000 | B4: Cash - Operating | C4: BS | D4: 428610.22 | E4: 401228.4 | F4: =E4-D4 -> -27381.82 | G4: =IF(D4=0,1,ABS(F4)/ABS(D4)) -> 0.063885131 | H4: =IF(ABS(F4)>=25000.0,"Yes","No") -> Yes | I4: Cash declined on scheduled AP pay-downs (JE-8871) and ordinary operating disbursements. | J4: JE_Activity_Notes JE-8871
A5: 1100 | B5: Accounts Receivable | C5: BS | D5: 1084220.6 | E5: 1162880.4 | F5: =E5-D5 -> 78659.85 | G5: =IF(D5=0,1,ABS(F5)/ABS(D5)) -> 0.072549676 | H5: =IF(ABS(F5)>=25000.0,"Yes","No") -> Yes | I5: AR rose on late-month shipments; INV-9918 billing-void status remains with original JE-8841 amounts still in the GL. | J5: JE-8841 / support S-01
A6: 1200 | B6: Inventory - Finished & WIP | C6: BS | D6: 1196880.4 | E6: 1248300.2 | F6: =E6-D6 -> 51419.78 | G6: =IF(D6=0,1,ABS(F6)/ABS(D6)) -> 0.042961502 | H6: =IF(ABS(F6)>=25000.0,"Yes","No") -> Yes | I6: Inventory TB vs CNT-AUG physical total (I-04/I-05); memo §4.4 physical-vs-book true-up applies. | J6: inventory I-04 / I-05
A7: 1650 | B7: Accumulated Depreciation | C7: BS | D7: 1628440.2 | E7: 1693320.6 | F7: =E7-D7 -> 64880.4 | G7: =IF(D7=0,1,ABS(F7)/ABS(D7)) -> 0.039842053 | H7: =IF(ABS(F7)>=25000.0,"Yes","No") -> Yes | I7: Accumulated depreciation increased by the monthly depreciation run JE-8860. | J7: JE-8860
A8: 2000 | B8: Accounts Payable | C8: BS | D8: 612880.4 | E8: 638440.55 | F8: =E8-D8 -> 25560.15 | G8: =IF(D8=0,1,ABS(F8)/ABS(D8)) -> 0.041704956 | H8: =IF(ABS(F8)>=25000.0,"Yes","No") -> Yes | I8: AP increased on receipt timing vs pay-downs; aging support is informational only. | J8: AP-AGE / JE-8871
A9: 5600 | B9: Maintenance & Repairs | C9: PL | D9: 48220.55 | E9: 118880.4 | F9: =E9-D9 -> 70659.85 | G9: =IF(D9=0,1,ABS(F9)/ABS(D9)) -> 1.4653 | H9: =IF(AND(ABS(F9)>=15000.0,G9>=0.1),"Yes","No") -> Yes | I9: Maintenance includes CAP-8821 CNC spindle rebuild (useful life 5 years) posted to expense; memo §4.5 CapEx test applies. | J9: capex C-01 / C-02 / JE-8810

Sheet Proposed_AJEs
A1: Proposed adjusting journal entries — 2026-08
A3: AJE_ID | B3: Line | C3: Account | D3: Account Name | E3: Debit | F3: Credit | G3: Amount_Check | H3: Rationale | I3: Support_Ref
A4: AJE-01 | B4: 1 | C4: 4100 | D4: Product Sales | E4: =Support_Reconcile!B13 -> 55280.4 | F4: 0 | G4: =E4+F4 -> 55280.4 | H4: Reverse voided INV-9918 revenue still in GL | I4: sales S-01 / JE-8841
A5: AJE-01 | B5: 2 | C5: 1100 | D5: Accounts Receivable | E5: 0 | F5: =Support_Reconcile!B13 -> 55280.4 | G5: =E5+F5 -> 55280.4 | H5: Reverse voided INV-9918 AR still in GL | I5: sales S-01 / JE-8841
A6: AJE-02 | B6: 1 | C6: 2200 | D6: Accrued Warranty | E6: =Support_Reconcile!B14 -> 34555.37 | F6: 0 | G6: =E6+F6 -> 34555.37 | H6: True warranty liability to W-04 governing support (see $6k detail-roll exception) | I6: warranty W-04
A7: AJE-02 | B7: 2 | C7: 5200 | D7: Warranty Expense | E7: 0 | F7: =Support_Reconcile!B14 -> 34555.37 | G7: =E7+F7 -> 34555.37 | H7: Offset warranty true-up to W-04 | I7: warranty W-04
A8: AJE-03 | B8: 1 | C8: 5300 | D8: Insurance Expense | E8: =Support_Reconcile!B15 -> 8417.25 | F8: 0 | G8: =E8+F8 -> 8417.25 | H8: Book August prepaid insurance amortization (annual/12) | I8: prepaid P-01 / memo §4.3
A9: AJE-03 | B9: 2 | C9: 1400 | D9: Prepaid Insurance | E9: 0 | F9: =Support_Reconcile!B15 -> 8417.25 | G9: =E9+F9 -> 8417.25 | H9: Amortize prepaid insurance | I9: prepaid P-01 / memo §4.3
A10: AJE-04 | B10: 1 | C10: 5100 | D10: Cost of Goods Sold | E10: =Support_Reconcile!B16 -> 28425.63 | F10: 0 | G10: =E10+F10 -> 28425.63 | H10: Write inventory book down to physical | I10: inventory I-04
A11: AJE-04 | B11: 2 | C11: 1200 | D11: Inventory - Finished & WIP | E11: 0 | F11: =Support_Reconcile!B16 -> 28425.63 | G11: =E11+F11 -> 28425.63 | H11: Write inventory book down to physical | I11: inventory I-04
A12: AJE-05 | B12: 1 | C12: 5400 | D12: Freight-In / Outbound | E12: =Support_Reconcile!B17 -> 41288.4 | F12: 0 | G12: =E12+F12 -> 41288.4 | H12: Accrue open freight support items | I12: freight F-04
A13: AJE-05 | B13: 2 | C13: 2210 | D13: Accrued Freight | E13: 0 | F13: =Support_Reconcile!B17 -> 41288.4 | G13: =E13+F13 -> 41288.4 | H13: Accrue open freight support items | I13: freight F-04
A14: AJE-06 | B14: 1 | C14: 2220 | D14: Accrued PTO | E14: =Support_Reconcile!B18 -> 23779.63 | F14: 0 | G14: =E14+F14 -> 23779.63 | H14: True PTO liability to HR support | I14: pto T-03
A15: AJE-06 | B15: 2 | C15: 5500 | D15: Payroll Benefits / PTO | E15: 0 | F15: =Support_Reconcile!B18 -> 23779.63 | G15: =E15+F15 -> 23779.63 | H15: Offset PTO true-up | I15: pto T-03
A16: AJE-07 | B16: 1 | C16: 1600 | D16: PP&E - Machinery | E16: =Support_Reconcile!B19 -> 62418.55 | F16: 0 | G16: =E16+F16 -> 62418.55 | H16: Capitalize CapEx-qualifying rebuild CAP-8821 | I16: capex C-01 / JE-8810
A17: AJE-07 | B17: 2 | C17: 5600 | D17: Maintenance & Repairs | E17: 0 | F17: =Support_Reconcile!B19 -> 62418.55 | G17: =E17+F17 -> 62418.55 | H17: Remove CapEx ticket from maintenance expense | I17: capex C-01 / JE-8810
A19: Total debits | E19: =SUM(E4:E17) -> 254165.23
A20: Total credits | F20: =SUM(F4:F17) -> 254165.23
A21: Out of balance (should be 0) | E21: =E19-F20 -> 0
A22: Balance check | E22: =IF(E21=0,"PASS","FAIL") -> PASS

Sheet Support_Reconcile
A1: TB vs support reconciliation
A3: Item | B3: TB_Amount | C3: Support_Amount | D3: Difference | E3: AJE_ID | F3: Disposition
A4: Accrued Warranty 2200 | B4: 182440.55 | C4: 147885.18 | D4: =B4-C4 -> 34555.37 | E4: AJE-02 | F4: True TB to W-04 governing support
A5: Prepaid Insurance amort | B5: 0 | C5: 101007 | D5: =ROUND(C5/12,2) -> 8417.25 | E5: AJE-03 | F5: Monthly = annual/12; book missing Aug amort
A6: Inventory 1200 | B6: 1248300.2 | C6: 1219874.6 | D6: =B6-C6 -> 28425.63 | E6: AJE-04 | F6: Write down to I-04 physical total
A7: Accrued Freight 2210 | B7: 0 | C7: 41288.4 | D7: =B7-C7 -> -41288.4 | E7: AJE-05 | F7: Accrue F-04 open total
A8: Accrued PTO 2220 | B8: 95220.18 | C8: 71440.55 | D8: =B8-C8 -> 23779.63 | E8: AJE-06 | F8: True TB to T-03
A9: Voided INV-9918 in AR/Sales | B9: 55280.4 | C9: 0 | D9: =B9-C9 -> 55280.4 | E9: AJE-01 | F9: Reverse billing-void amounts still in GL
A10: CAP-8821 in Maintenance | B10: 62418.55 | C10: 62418.55 | D10: =B10-C10 -> 0 | E10: AJE-07 | F10: Reclass to PP&E 1600 per §4.5
A12: AJE amount bridge (live formulas from rows above)
A13: AJE-01 Void reverse | B13: =ABS(D9) -> 55280.4
A14: AJE-02 Warranty true-up (W-04 basis) | B14: =ABS(D4) -> 34555.37
A15: AJE-03 Prepaid amort | B15: =D5 -> 8417.25
A16: AJE-04 Inventory write-down | B16: =ABS(D6) -> 28425.63
A17: AJE-05 Freight accrual | B17: =ABS(D7) -> 41288.4
A18: AJE-06 PTO true-up | B18: =ABS(D8) -> 23779.63
A19: AJE-07 CapEx reclass | B19: =ABS(C10) -> 62418.55
A21: Warranty source exception (open support inconsistency)
A22: Detail roll W-01+W-02+W-03 | B22: 153885.18
A23: W-04 governing support total | B23: 147885.18
A24: Variance (detail roll − W-04) | B24: =B22-B23 -> 6000
A25: Selected governing figure | B25: =B23 -> 147885.18 | C25: W-04
A26: Selection reason | B26: W-04 status=Support and notes='Governing support total' establish W-04 as the controlling support ending under memo §4.2; AJE-02 trues TB 2200 to W-04.
A29: Open exception treatment | B29: Detail roll $153,885.18 vs W-04 $147,885.18 leaves an unexplained $6,000.00 source gap. Documented as an open reconciliation exception — not a second AJE and not silently ignored.
A32: Exception amount check (should equal variance) | B32: =IF(ABS(B24-6000.0)<0.005,"PASS","FAIL") -> PASS

Sheet Close_Decision
A1: Close readiness decision
A3: Status | B3: Ready with AJEs
A5: Decision notes
A6: Plant_Notes assert a clean close with no AJEs. Under flux_threshold_and_aje_memo.txt hierarchy, that note does not clear mandatory AJE categories. Seven AJEs are proposed (void reverse, warranty to W-04, prepaid amort, inventory write-down, freight accrual, PTO true-up, CapEx reclass). The $6,000.00 warranty detail-roll vs W-04 gap is an open source exception documented on Support_Reconcile; it does not block quantification of AJE-02 on the W-04 basis. Soft close may proceed as Ready with AJEs once those entries post. Status is not Ready (AJEs remain) and not Hold close (amounts are fully quantified from TB + governing support).
A14: Path matrix check
A15: Ready? | B15: No — required AJEs outstanding
A16: Ready with AJEs? | B16: Yes — pack proposes all section 4 AJEs
A17: Hold close? | B17: No — quantification complete on governing support; $6k warranty source gap disclosed as exception

Sheet Values_Snapshot
A1: Rounded key amounts — live links to calculation sheets (not re-typed)
A3: VOID_JE_AMT | B3: =Support_Reconcile!B13 -> 55280.4
A4: WARRANTY_AJE | B4: =Support_Reconcile!B14 -> 34555.37
A5: PREPAID_AUG_AMORT | B5: =Support_Reconcile!B15 -> 8417.25
A6: INV_WRITE_DOWN | B6: =Support_Reconcile!B16 -> 28425.63
A7: FREIGHT_OPEN | B7: =Support_Reconcile!B17 -> 41288.4
A8: PTO_AJE | B8: =Support_Reconcile!B18 -> 23779.63
A9: CAPEX_REBUILD | B9: =Support_Reconcile!B19 -> 62418.55
A10: AJE_TOTAL_DEBITS | B10: =Proposed_AJEs!E19 -> 254165.23
A11: AJE_OUT_OF_BALANCE | B11: =Proposed_AJEs!E21 -> 0
A12: WARRANTY_DETAIL_ROLL | B12: =Support_Reconcile!B22 -> 153885.18
A13: WARRANTY_W04 | B13: =Support_Reconcile!B23 -> 147885.18
A14: WARRANTY_SOURCE_VARIANCE | B14: =Support_Reconcile!B24 -> 6000
A15: CLOSE_STATUS | B15: =Close_Decision!B3 -> Ready with AJEs
