Workbook

Sheet Assumptions
A1: Whitaker Precision Components: credit decision assumptions
A2: Application CL-2026-4418 | Financials as-of 2026-06-30 | Committee 2026-09-18 | Governing: credit_policy_and_exception_memo.txt
A4: Parameter | B4: Value | C4: Source / rule
A5: Requested commitment | B5: 2847500 | C5: whitaker-precision-components_borrower_financials.xlsx Application
A6: Requested tenor (months) | B6: 84 | C6: whitaker-precision-components_borrower_financials.xlsx Application
A7: Pricing factor per $1,000 / month | B7: 16.42 | C7: credit_policy_and_exception_memo.txt §4
A8: Existing bank annual debt service | B8: 412880.4 | C8: whitaker-precision-components_borrower_financials.xlsx Debt_Schedule
A9: Existing bank UPB | B9: 2184220.5 | C9: whitaker-precision-components_borrower_financials.xlsx Debt_Schedule
A10: Reported EBITDA FY2025 | B10: 1248620.2 | C10: whitaker-precision-components_borrower_financials.xlsx Income
A11: One-time parcel gain in reported EBITDA | B11: 185400 | C11: whitaker-precision-components_borrower_financials.xlsx Income
A12: Owner add-back claimed (RM) | B12: 210000 | C12: whitaker-precision-components_borrower_financials.xlsx RM_Notes
A13: Owner add-back allowed (policy) | B13: 84220.55 | C13: credit_policy_and_exception_memo.txt §3(b)
A14: Related-party rent add-back claimed | B14: 96000 | C14: credit_policy_and_exception_memo.txt §3(c) — disallow
A15: Minimum DSCR (Approve) | B15: 1.25 | C15: credit_policy_and_exception_memo.txt §5
A16: Conditional DSCR floor | B16: 1.15 | C16: credit_policy_and_exception_memo.txt §5
... A20: Fixture advance rate | B20: 0.5 | C20: credit_policy_and_exception_memo.txt §6
A21: Hierarchy | B21: Memo supersedes RM notes | C21: credit_policy_and_exception_memo.txt §1

Sheet EBITDA_Build
A1: Adjusted EBITDA build (policy basis)
A2: Sources: whitaker-precision-components_borrower_financials.xlsx Income; rules in credit_policy_and_exception_memo.txt §3
A4: Step | B4: Amount | C4: Include | D4: Rationale
A5: Reported EBITDA FY2025 | B5: 1248620.2 | C5: Yes | D5: Starting point per memo §3
A6: Less: one-time parcel sale gain | B6: -185400 | C6: Yes | D6: Non-operating gain embedded in reported EBITDA
A7: Plus: owner add-back allowed | B7: 84220.55 | C7: Yes | D7: Capped at 84,220.55; not RM claim 210,000.00
A8: Related-party rent add-back (claimed) | B8: 96000 | C8: No | D8: Disallowed — continuing cash rent; no CA exception
A9: Management EBITDA (RM — not used) | B9: 1554620.2 | C9: No | D9: Keeps gain; adds full owner + rent — superseded
A11: Adjusted EBITDA | B11: =B5+B6+B7 -> 1147440.7 | C11: Policy measure for DSCR / leverage
A13: Counterfactual: if RM management EBITDA were used (prohibited) | B13: 1554620.2

Sheet Collateral_LTV
A1: Collateral eligibility, advances, and LTV
A2: Sources: whitaker-precision-components_collateral_schedule.csv; eligibility/advances per credit_policy_and_exception_memo.txt §6–7
A4: Asset ID | B4: Description | C4: Category | D4: NOLV | E4: Eligible | F4: Advance % | G4: Bankable | H4: Disposition
A5: CNC-4418-01 | B5: Haas VF-4SS | C5: CNC_new | D5: 485220.18 | E5: Yes | F5: 0.8 | G5: 388176.14 | H5: Eligible — 80% NOLV
A6: CNC-4418-02 | B6: DMG MORI NLX2500 | C6: CNC_new | D6: 612880.4 | E6: Yes | F6: 0.8 | G6: 490304.32 | H6: Eligible — 80% NOLV
A7: CNC-4418-03 | B7: Mazak Integrex i-200S | C7: CNC_new | D7: 728440.55 | E7: Yes | F7: 0.8 | G7: 582752.44 | H7: Eligible — 80% NOLV
A8: FIX-4418-10 | B8: Fixtures / tombstones | C8: Fixtures | D8: 214880.4 | E8: Yes | F8: 0.5 | G8: 107440.2 | H8: Eligible — 50% NOLV (not RM 70%)
A9: BLD-ROCK-01 | B9: Plant building (related) | C9: RealEstate_related | D9: 1850000 | E9: No | F9: 0 | G9: 0 | H9: Ineligible — related-party title
A10: MILL-1998-04 | B10: Bridgeport Series I | C10: Obsolete_manual | D10: 12400.55 | E10: No | F10: 0 | G10: 0 | H10: Ineligible — age cutoff
A11: SOFT-4418 | B11: Install / freight / deposits | C11: SoftCost | D11: 95220.18 | E11: No | F11: 0 | G11: 0 | H11: Ineligible — soft costs
A12: FL-LEASE-02 | B12: Toyota forklift | C12: Leased_equipment | D12: 28440 | E12: No | F12: 0 | G12: 0 | H12: Ineligible — lessor title
A13: LEASEHOLD-IMP | B13: Leasehold improvements | C13: Leasehold | D13: 22440.55 | E13: No | F13: 0 | G13: 0 | H13: Ineligible — related realty
A15: Eligible NOLV | B15: =D5+D6+D7+D8 -> 2041421.5 | C15: Must equal 2,041,421.53
A16: Bankable collateral | B16: =G5+G6+G7+G8 -> 1568673.1 | C16: Must equal 1,568,673.10
A17: 75% of eligible NOLV | B17: =ROUND(B15*0.75,2) -> 1531066.1
A18: Binding maximum commitment | B18: =MIN(B16,B17) -> 1531066.1 | C18: min(bankable, 75% eligible NOLV)
A20: LTV at full request | B20: =ROUND(2847500.0/B15,4) -> 1.3949 | C20: Fails max 0.75
A21: LTV at binding max | B21: =ROUND(B18/B15,4) -> 0.75 | C21: Passes at 0.75

Sheet DSCR_Leverage
A1: DSCR and leverage tests
A2: Debt service factor 16.42 per $1,000 / month (credit_policy_and_exception_memo.txt §4–5)
A4: Metric | B4: Full request | C4: Sized commitment | D4: Threshold | E4: Result
A5: Commitment tested | B5: 2847500 | C5: =Collateral_LTV!B18 -> 1531066.1 | D5: n/a
A6: Proposed annual debt service | B6: =ROUND(ROUND(B5/1000*16.42,2)*12,2) -> 561071.4 | C6: =ROUND(ROUND(C5/1000*16.42,2)*12,2) -> 301681.32 | D6: Factor 16.42
A7: Existing bank annual DS | B7: 412880.4 | C7: =B7
A8: Total annual debt service | B8: =ROUND(B6+B7,2) -> 973951.8 | C8: =ROUND(C6+C7,2) -> 714561.72
A9: Adjusted EBITDA | B9: =EBITDA_Build!B11 -> 1147440.7 | C9: =B9 -> 1147440.7
A10: DSCR | B10: =ROUND(B9/B8,4) -> 1.1781 | C10: =ROUND(C9/C8,4) -> 1.6058 | D10: 1.25 | E10: Full ask fails 1.25; sized passes
A11: Total debt (UPB + commitment) | B11: =ROUND(2184220.55+B5,2) -> 5031720.5 | C11: =ROUND(2184220.55+C5,2) -> 3715286.7
A12: Leverage (Total debt / Adj EBITDA) | B12: =ROUND(B11/B9,4) -> 4.3852 | C12: =ROUND(C11/C9,4) -> 3.2379 | D12: 3.5 | E12: Sized passes 3.50x
A14: Path trigger notes
A15: Full-ask DSCR 1.1781 is below 1.25 but at/above 1.15; full-ask LTV 1.3949 exceeds 0.75. After sizing to binding max, DSCR 1.6058 and LTV 0.75 clear Approve thresholds → Conditional path.

Sheet Exceptions
A1: Exception and conflict log
A3: Item | B3: Source conflict | C3: Governing treatment | D3: Impact
A4: RM Approve as requested | B4: whitaker-precision-components_borrower_financials.xlsx RM_Notes / Application | C4: credit_policy_and_exception_memo.txt §1 — memo supersedes; path not Approve at full ask | D4: Blocks full-ask Approve
A5: Management EBITDA | B5: whitaker-precision-components_borrower_financials.xlsx Income / RM_Notes | C5: credit_policy_and_exception_memo.txt §3 — strip gain; cap owner add-back; disallow rent add-back | D5: Adj EBITDA 1,147,440.73 vs MGMT 1,554,620.18
A6: Related-party building pledged | B6: whitaker-precision-components_collateral_schedule.csv BLD-ROCK-01 | C6: credit_policy_and_exception_memo.txt §6 — ineligible collateral | D6: Removed from eligible NOLV / bankable
A7: Soft costs 100% advance claim | B7: whitaker-precision-components_collateral_schedule.csv SOFT-4418 | C7: credit_policy_and_exception_memo.txt §6 — soft costs 0% advance | D7: Excluded from bankable
A8: Fixture RM advance 70% | B8: whitaker-precision-components_collateral_schedule.csv FIX-4418-10 | C8: credit_policy_and_exception_memo.txt §6 — fixtures 50% | D8: Bankable uses 50%
A9: Leased forklift pledged | B9: whitaker-precision-components_collateral_schedule.csv FL-LEASE-02 | C9: credit_policy_and_exception_memo.txt §6 — lessor title ineligible | D9: Excluded
A10: No personal guaranty offered | B10: whitaker-precision-components_borrower_financials.xlsx Application | C10: credit_policy_and_exception_memo.txt §8 — Conditional requires unlimited PG | D10: Condition on recommendation
A11: 84-month tenor requested | B11: whitaker-precision-components_borrower_financials.xlsx Application | C11: credit_policy_and_exception_memo.txt §8 — Conditional shortens to 60 months | D11: Condition on recommendation

Sheet Credit_Decision
A1: Whitaker Precision Components — credit path decision
A2: Committee 2026-09-18 | Application CL-2026-4418
A4: Path | B4: Approve with conditions
A5: Recommended commitment (USD) | B5: =Collateral_LTV!B18 -> 1531066.1
A6: Requested commitment (not approved) | B6: 2847500
A7: DSCR at recommended commitment | B7: =DSCR_Leverage!C10 -> 1.6058
A8: LTV at recommended commitment | B8: =Collateral_LTV!B21 -> 0.75
A9: Leverage at recommended commitment | B9: =DSCR_Leverage!C12 -> 3.2379
A11: Conditions (Conditional path)
A12: 1. Cap commitment at binding maximum (Collateral_LTV binding max; 1,531,066.15).
A13: 2. Tenor 60 months (not 84).
A14: 3. Unlimited personal guaranty of the principal owner.
A15: 4. Quarterly DSCR covenant at 1.25x on Adjusted EBITDA per memo §3.
A16: 5. Pledge limited to eligible CNC and fixtures; exclude related-party realty, leases, soft costs, obsolete mill.
A17: 6. Present to committee (Conditional sizing path) even though sized amount is under officer limit.
A19: Explicit do-nots
A20: Do not approve the full requested commitment.
A21: Do not treat Whitaker Realty LLC building or leasehold improvements as eligible collateral.
A22: Do not measure DSCR on management EBITDA that retains the parcel gain or related-party rent add-back.
A23: Do not Decline solely because the request exceeds bankable collateral — size to binding max under Conditional.

Sheet Notes
A1: Committee notes and source citations
A3: Governing hierarchy: credit_policy_and_exception_memo.txt §1 controls over RM Approve-as-requested language on whitaker-precision-components_borrower_financials.xlsx RM_Notes.
A4: Adjusted EBITDA 1,147,440.73 = reported 1,248,620.18 − gain 185,400.00 + allowed owner 84,220.55 (whitaker-precision-components_borrower_financials.xlsx; credit_policy_and_exception_memo.txt §3).
A5: Eligible NOLV 2,041,421.53; bankable 1,568,673.10; 75% cap 1,531,066.15; binding commitment 1,531,066.15 (whitaker-precision-components_collateral_schedule.csv; credit_policy_and_exception_memo.txt §6–7).
A6: Full-ask DSCR 1.1781 and LTV 1.3949 fail Approve tests; sized DSCR 1.6058, LTV 0.75, leverage 3.2379 pass (credit_policy_and_exception_memo.txt §5, §8).
A7: Path selected: Approve with conditions with commitment 1,531,066.15 and 60-month tenor plus PG and DSCR covenant.
A8: Citations above appear earlier on this Notes tab than the committee path recommendation that follows.
A9: Committee path recommendation: Approve with conditions at $1,531,066.15 with conditions listed on Credit_Decision — not Approve at $2,847,500.00, and not Decline.
