Workbook

Sheet Assumptions
A1: Ironclad Telematics — growth-equity valuation inputs | B1: Value
A3: Pre-money valuation | B3: 145000000
A4: Primary proceeds | B4: 35000000
A5: Post-money before pool refresh | B5: 180000000
A6: Calendar 2024 cohort TTM | B6: 26041611
A7: Municipal pilot excluded | B7: 2040000
A8: Normalized model ARR | B8: 24001611
A9: Brief headline run-rate (not used) | B9: 28400000
A10: Fully diluted pre-money shares | B10: 18400000
A11: Quorum Ventures Series Seed preferred shares | B11: 4600000
A12: Growth round price per share | B12: 7.8804348
A13: Note A cap price | B13: 2.7173913
A14: Note A discounted round price | B14: 6.3043478
... A38: Hartwell Partners lead primary proceeds | B38: 26250000

Sheet Fleet Cohort Build
A1: cohort_id | B1: fiscal_month_label | C1: calendar_quarter | D1: starting_arr | E1: vehicle_count | F1: gross_retention_pct | G1: expansion_arr | H1: churn_arr | I1: ending_arr | J1: include_in_model | K1: adjusted_ending_arr | L1: source_treatment
A2: IC-2019-01 | B2: FY25-M07 | C2: 2024-Q4 | D2: 360570.44 | E2: 46 | F2: 93.1 | G2: 38887.27 | H2: 21065.35 | I2: =D2*F2/100+G2-H2 -> 353513 | J2: 1 | K2: =I2*J2 -> 353513 | L2: Included
A3: IC-2020-02 | B3: FY25-M07 | C3: 2024-Q4 | D3: 428386.57 | E3: 57 | F3: 92.4 | G3: 47728.15 | H3: 23892.79 | I3: =D3*F3/100+G3-H3 -> 419664.55 | J3: 1 | K3: =I3*J3 -> 419664.55 | L3: Included
A4: IC-2020-04 | B4: FY25-M07 | C4: 2024-Q4 | D4: 575839.21 | E4: 67 | F4: 93.8 | G4: 59893.98 | H4: 27543.73 | I4: =D4*F4/100+G4-H4 -> 572487.43 | J4: 1 | K4: =I4*J4 -> 572487.43 | L4: Included
A5: IC-2021-01 | B5: FY25-M07 | C5: 2024-Q4 | D5: 715429.6 | E5: 76 | F5: 94.7 | G5: 69826.46 | H5: 31796.74 | I5: =D5*F5/100+G5-H5 -> 715541.55 | J5: 1 | K5: =I5*J5 -> 715541.55 | L5: Included
A6: IC-2021-03 | B6: FY25-M07 | C6: 2024-Q4 | D6: 843032.6 | E6: 91 | F6: 94.1 | G6: 87700.1 | H6: 39029.03 | I6: =D6*F6/100+G6-H6 -> 841964.75 | J6: 1 | K6: =I6*J6 -> 841964.75 | L6: Included
A7: IC-2022-01 | B7: FY25-M07 | C7: 2024-Q4 | D7: 1052585 | E7: 106 | F7: 95.3 | G7: 103664.07 | H7: 43621.14 | I7: =D7*F7/100+G7-H7 -> 1063156.4 | J7: 1 | K7: =I7*J7 -> 1063156.4 | L7: Included
A8: IC-2022-04 | B8: FY25-M07 | C8: 2024-Q4 | D8: 1211415.3 | E8: 120 | F8: 94.9 | G8: 120909.7 | H8: 47617.97 | I8: =D8*F8/100+G8-H8 -> 1222924.8 | J8: 1 | K8: =I8*J8 -> 1222924.8 | L8: Included
A9: IC-2023-02 | B9: FY25-M07 | C9: 2024-Q4 | D9: 1485096.7 | E9: 135 | F9: 95.8 | G9: 141232.9 | H9: 53455.45 | I9: =D9*F9/100+G9-H9 -> 1510500.1 | J9: 1 | K9: =I9*J9 -> 1510500.1 | L9: Included
A10: IC-2023-04 | B10: FY25-M07 | C10: 2024-Q4 | D10: 1666217.5 | E10: 152 | F10: 95.5 | G10: 165044.15 | H10: 59770.94 | I10: =D10*F10/100+G10-H10 -> 1696510.9 | J10: 1 | K10: =I10*J10 -> 1696510.9 | L10: Included
A11: IC-MUNI-24 | B11: FY25-M07 | C11: 2024-Q4 | D11: 2260320 | E11: 304 | F11: 100 | G11: 0 | H11: 0 | I11: =D11*F11/100+G11-H11 -> 2260320 | J11: 0 | K11: =I11*J11 -> 0 | L11: Excluded: pilot_non_recurring per brief Footnote 1; MetroLink Transit Authority 12-month deployment; procurement has not approved renewal. Exclude from run-rate under sponsor brief Footnote 1 using the brief's $2,040,000 award-year annualized exclusion (not this row's ending_arr). Current-period ending_arr reflects mid-pilot vehicle adds and rate schedule.
A14: calendar_quarter | B14: source_rollup_arr | C14: source
A15: 2024-Q1 | B15: 5712480.3 | C15: ironclad_fleet_cohort_arr.xlsx / Fleet Rollup
A16: 2024-Q2 | B16: 6184925.8 | C16: ironclad_fleet_cohort_arr.xlsx / Fleet Rollup
A17: 2024-Q3 | B17: 6752340.5 | C17: ironclad_fleet_cohort_arr.xlsx / Fleet Rollup
A18: 2024-Q4 | B18: 7391864.2 | C18: ironclad_fleet_cohort_arr.xlsx / Fleet Rollup
A20: Calendar 2024 TTM | B20: =SUM(B15:B18) -> 26041611
A21: Normalized model ARR | B21: =B20-Assumptions!B7 -> 24001611

Sheet Revenue Forecast
A1: period | B1: growth_rate | C1: arr | D1: fcf_margin | E1: free_cash_flow
A2: Base / normalized TTM | B2: 0 | C2: ='Fleet Cohort Build'!B21 -> 24001611 | D2: 0.2 | E2: =C2*D2 -> 4800322.2
A3: Year 1 | B3: 0.26 | C3: =C2*(1+B3) -> 30242030 | D3: =Assumptions!B24 -> 0.2 | E3: =C3*D3 -> 6048405.9
A4: Year 2 | B4: 0.22 | C4: =C3*(1+B4) -> 36895276 | D4: =Assumptions!B24 -> 0.2 | E4: =C4*D4 -> 7379055.2
A5: Year 3 | B5: 0.18 | C5: =C4*(1+B5) -> 43536426 | D5: =Assumptions!B24 -> 0.2 | E5: =C5*D5 -> 8707285.2
A6: Year 4 | B6: 0.15 | C6: =C5*(1+B6) -> 50066890 | D6: =Assumptions!B24 -> 0.2 | E6: =C6*D6 -> 10013378
A7: Year 5 | B7: 0.12 | C7: =C6*(1+B7) -> 56074916 | D7: =Assumptions!B24 -> 0.2 | E7: =C7*D7 -> 11214983

Sheet DCF Build
A1: year | B1: arr | C1: fcf | D1: discount_factor_13pct | E1: pv_13pct | F1: discount_factor_15pct | G1: pv_15pct
A2: 1 | B2: ='Revenue Forecast'!C3 -> 30242030 | C2: =B2*Assumptions!B24 -> 6048405.9 | D2: =1/(1+Assumptions!B25)^A2 -> 0.88495575 | E2: =C2*D2 -> 5352571.6 | F2: =1/(1+Assumptions!B26)^A2 -> 0.86956522 | G2: =C2*F2 -> 5259483.4
A3: 2 | B3: ='Revenue Forecast'!C4 -> 36895276 | C3: =B3*Assumptions!B24 -> 7379055.2 | D3: =1/(1+Assumptions!B25)^A3 -> 0.78314668 | E3: =C3*D3 -> 5778882.6 | F3: =1/(1+Assumptions!B26)^A3 -> 0.75614367 | G3: =C3*F3 -> 5579625.9
A4: 3 | B4: ='Revenue Forecast'!C5 -> 43536426 | C4: =B4*Assumptions!B24 -> 8707285.2 | D4: =1/(1+Assumptions!B25)^A4 -> 0.69305016 | E4: =C4*D4 -> 6034585.4 | F4: =1/(1+Assumptions!B26)^A4 -> 0.65751623 | G4: =C4*F4 -> 5725181.3
A5: 4 | B5: ='Revenue Forecast'!C6 -> 50066890 | C5: =B5*Assumptions!B24 -> 10013378 | D5: =1/(1+Assumptions!B25)^A5 -> 0.61331873 | E5: =C5*D5 -> 6141392.2 | F5: =1/(1+Assumptions!B26)^A5 -> 0.57175325 | G5: =C5*F5 -> 5725181.3
A6: 5 | B6: ='Revenue Forecast'!C7 -> 56074916 | C6: =B6*Assumptions!B24 -> 11214983 | D6: =1/(1+Assumptions!B25)^A6 -> 0.54275994 | E6: =C6*D6 -> 6087043.6 | F6: =1/(1+Assumptions!B26)^A6 -> 0.49717674 | G6: =C6*F6 -> 5575828.8

Sheet Cap Table Pro Forma
A1: holder / security | B1: pre_shares | C1: principal_or_primary | D1: conversion_or_round_price | E1: conversion_shares | F1: primary_shares | G1: post_shares | H1: post_ownership | I1: treatment
A2: Existing holders (including available pool) | B2: =Assumptions!B10 -> 18400000 | C2: 0 | D2: 0 | E2: 0 | F2: 0 | G2: =B2+E2+F2 -> 18400000 | H2: =G2/SUM($G$2:$G$7) -> 0.67665166 | I2: Pre-money FD from ironclad_cap_table.csv
A3: Octavian Capital — Note A | B3: 0 | C3: =Assumptions!B32 -> 4200000 | D3: =Assumptions!B15 -> 2.7174 | E3: =Assumptions!B17 -> 1545600 | F3: 0 | G3: =B3+E3+F3 -> 1545600 | H3: =G3/SUM($G$2:$G$7) -> 0.05683874 | I3: Displayed first per brief; cap price wins
A4: Vesper Growth — Note B | B4: 0 | C4: =Assumptions!B35 -> 2800000 | D4: =Assumptions!B16 -> 3.5326 | E4: =Assumptions!B18 -> 792615.38 | F4: 0 | G4: =B4+E4+F4 -> 792615.38 | H4: =G4/SUM($G$2:$G$7) -> 0.02914807 | I4: Cap-only conversion
A5: Quorum Ventures — pro-rata primary | B5: 0 | C5: =Assumptions!B37 -> 8750000 | D5: =Assumptions!B12 -> 7.8804 | E5: 0 | F5: =Assumptions!B37/Assumptions!B12 -> 1110344.8 | G5: =B5+E5+F5 -> 1110344.8 | H5: =G5/SUM($G$2:$G$7) -> 0.04083243 | I5: Full pro-rata modeling case
A6: Hartwell Partners — lead primary | B6: 0 | C6: =Assumptions!B38 -> 26250000 | D6: =Assumptions!B12 -> 7.8804 | E6: 0 | F6: =Assumptions!B38/Assumptions!B12 -> 3331034.5 | G6: =B6+E6+F6 -> 3331034.5 | H6: =G6/SUM($G$2:$G$7) -> 0.12249728 | I6: Primary remainder
A7: Incremental option pool refresh | B7: 0 | C7: 0 | D7: 0 | E7: 0 | F7: =Assumptions!B23 -> 2013126.6 | G7: =B7+E7+F7 -> 2013126.6 | H7: =G7/SUM($G$2:$G$7) -> 0.07403182 | I7: 12% post-money sponsor case

Sheet Valuation Summary
A1: method | B1: enterprise_value | C1: basis
A2: Downside revenue multiple | B2: =Assumptions!B8*Assumptions!B31 -> 96006443 | C2: 4.0x normalized TTM
A3: NTM revenue multiple — low | B3: ='Revenue Forecast'!C3*Assumptions!B29 -> 1.3608913e+08 | C3: 4.5x Year 1 NTM
A4: NTM revenue multiple — high | B4: ='Revenue Forecast'!C3*Assumptions!B30 -> 1.8145218e+08 | C4: 6.0x Year 1 NTM
A5: DCF — 13% WACC | B5: =SUM('DCF Build'!E2:E6)+'DCF Build'!C6*(1+0.03)/(0.13-0.03)/(1+0.13)^5 -> 92091025 | C5: Five-year FCF plus terminal value
A6: DCF — 15% WACC | B6: =SUM('DCF Build'!G2:G6)+'DCF Build'!C6*(1+0.03)/(0.15-0.03)/(1+0.15)^5 -> 75724498 | C6: Five-year FCF plus terminal value
A7: Midpoint revenue-multiple valuation | B7: =(B3+B4)/2 -> 1.5877066e+08 | C7: Average of 4.5x–6.0x NTM cases
A8: Midpoint DCF-implied valuation | B8: =(B5+B6)/2 -> 83907761 | C8: Average of 13%–15% WACC cases
A9: Multiple vs DCF midpoint variance | B9: =B7-B8 -> 74862894 | C9: Reconciliation of market and DCF views
A10: Term-sheet pre-money | B10: 145000000 | C10: growth_equity_diligence_brief.txt
A11: Term-sheet post-money before pool | B11: 180000000 | C11: growth_equity_diligence_brief.txt

Sheet Sensitivity
A1: net_retention | B1: fleet_growth | C1: implied_ntm_value | D1: method | F1: normalized_ttm | G1: =Assumptions!B8 -> 24001611
A2: 1.04 | B2: 0.2 | C2: =$G$1*A2*(1+B2)*$G$2 -> 1.5576085e+08 | D2: Peer-median NTM multiple from Assumptions; NRR and fleet growth varied | F2: selected_multiple | G2: =Assumptions!B28 -> 5.2
A3: 1.04 | B3: 0.26 | C3: =$G$1*A3*(1+B3)*$G$2 -> 1.635489e+08 | D3: Peer-median NTM multiple from Assumptions; NRR and fleet growth varied
A4: 1.04 | B4: 0.32 | C4: =$G$1*A4*(1+B4)*$G$2 -> 1.7133694e+08 | D4: Peer-median NTM multiple from Assumptions; NRR and fleet growth varied
A5: 1.08 | B5: 0.2 | C5: =$G$1*A5*(1+B5)*$G$2 -> 1.6175166e+08 | D5: Peer-median NTM multiple from Assumptions; NRR and fleet growth varied
A6: 1.08 | B6: 0.26 | C6: =$G$1*A6*(1+B6)*$G$2 -> 1.6983924e+08 | D6: Peer-median NTM multiple from Assumptions; NRR and fleet growth varied
A7: 1.08 | B7: 0.32 | C7: =$G$1*A7*(1+B7)*$G$2 -> 1.7792682e+08 | D7: Peer-median NTM multiple from Assumptions; NRR and fleet growth varied
A8: 1.12 | B8: 0.2 | C8: =$G$1*A8*(1+B8)*$G$2 -> 1.6774246e+08 | D8: Peer-median NTM multiple from Assumptions; NRR and fleet growth varied
A9: 1.12 | B9: 0.26 | C9: =$G$1*A9*(1+B9)*$G$2 -> 1.7612958e+08 | D9: Peer-median NTM multiple from Assumptions; NRR and fleet growth varied
A10: 1.12 | B10: 0.32 | C10: =$G$1*A10*(1+B10)*$G$2 -> 1.845167e+08 | D10: Peer-median NTM multiple from Assumptions; NRR and fleet growth varied

Sheet Option pool cases
A1: case | B1: target_pct | C1: existing_available | D1: fd_before_refresh | E1: incremental_refresh | F1: fd_post | G1: combined_pool_pct | H1: treatment
A2: Counsel reference | B2: 0.1 | C2: =Assumptions!B19 -> 1250000 | D2: =Assumptions!B20 -> 25179595 | E2: =MAX((B2*D2-C2)/(1-B2),0) -> 1408843.9 | F2: =D2+E2 -> 26588439 | G2: =(C2+E2)/F2 -> 0.1 | H2: Alternate only; cap-table note
A3: Sponsor term sheet | B3: 0.12 | C3: =Assumptions!B19 -> 1250000 | D3: =Assumptions!B20 -> 25179595 | E3: =MAX((B3*D3-C3)/(1-B3),0) -> 2013126.6 | F3: =D3+E3 -> 27192721 | G3: =(C3+E3)/F3 -> 0.12 | H3: Primary pro forma case

Sheet Notes
A1: Workpaper notes — source conflicts, judgments, and citations
A2: topic | B2: detail
A3: ARR bridge — Fleet Rollup TTM | B3: Source: ironclad_fleet_cohort_arr.xlsx / Fleet Rollup. Sum of calendar 2024 fleet_arr = $26,041,610.80. Treatment: used as TTM reference before Footnote 1 exclusion. Cite: growth_equity_diligence_brief.txt (ARR bridge paragraph).
A4: Fleet Rollup vs Cohort Detail | B4: Sources: growth_equity_diligence_brief.txt — ARR/run-rate methodology (Fleet Rollup vs Cohort Detail recognition guidance); ironclad_fleet_cohort_arr.xlsx — Fleet Rollup (2024 quarterly fleet_arr totals), Cohort Detail (ending_arr by billing cohort), Recognition Bridge (fleet_arr identity), and Definitions (field definitions). Issue: Cohort Detail ending_arr (gross contracted ARR by billing cohort) does not equal Fleet Rollup fleet_arr (finance-recognized subscription ARR) at the quarterly total. Vehicle counts also differ because Fleet Rollup includes onboarding units not yet tagged to a cohort_id. Treatment: board TTM uses Fleet Rollup fleet_arr. Bridge identity on Recognition Bridge: fleet_arr = SUMIF(Cohort Detail ending_arr by calendar_quarter) − IC-2023-02-XP duplicate − recognition_timing_adj. Rationale: contracted billing view vs subscription-ledger recognition; timing adj covers implementation deferrals and multi-year billings not yet in the finance rollup. Consequence: do not substitute the raw Cohort Detail sum for board TTM.
A5: MetroLink MUNI exclusion vs Cohort Detail | B5: Source: growth_equity_diligence_brief.txt Footnote 1 states $2,040,000 award-year annualized exclusion for MetroLink Transit Authority (pilot_non_recurring). Source schedule: ironclad_fleet_cohort_arr.xlsx / Cohort Detail row IC-MUNI-24 shows higher 2024 ending_arr (Q1 $2,150,160; Q2 $2,182,800; Q3 $2,235,840; Q4 $2,260,320) after mid-pilot vehicle adds and rate schedule. Issue: $2,040,000 cannot be tied to any single IC-MUNI-24 ending_arr cell. Treatment: model subtracts the brief's $2,040,000 from Fleet Rollup TTM (normalized ARR $24,001,610.80). Rationale: Footnote 1 is the governing sponsor/diligence instruction. Consequence: if a reviewer instead excluded current-period IC-MUNI-24 ending_arr (or a TTM average thereof), normalized ARR would be lower by roughly the excess of cohort MUNI over $2,040,000; flag for board/committee review.
A6: Management headline run-rate | B6: Source: growth_equity_diligence_brief.txt quotes $28,400,000. Issue: exceeds Fleet Rollup TTM. Treatment: disclosed only; not used as valuation base.
A7: Fiscal vs calendar period labels | B7: Sources: growth_equity_diligence_brief.txt — Footnote 2; ironclad_fleet_cohort_arr.xlsx — Cohort Detail fiscal_month_label vs calendar_quarter columns. Issue: FY25-M01/M04/M07 look like calendar 2025 but map to 2024-Q2/Q3/Q4. Treatment: calendar_quarter governs trailing-period selection on Fleet Cohort Build.
A8: Duplicate expansion row | B8: Sources: growth_equity_diligence_brief.txt — duplicate expansion / retention guidance; ironclad_fleet_cohort_arr.xlsx — Cohort Detail row IC-2023-02-XP (and Recognition Bridge duplicate column). Issue: repeats IC-2022-04 fleet amendment. Treatment: IC-2023-02-XP is excluded from retention math because it duplicates the prior fleet amendment and is already captured in the earlier row. Implementation: include_in_model = FALSE on Fleet Cohort Build; also removed from the Recognition Bridge duplicate column.
A9: Convertible note mechanics | B9: Sources: growth_equity_diligence_brief.txt — note conversion order and mechanics; ironclad_cap_table.csv — Octavian Capital and Vesper Growth convertible note rows. Octavian Capital Note A: $4,200,000, $50,000,000 cap, 20% discount — lower of cap price and discounted round price; displayed before Note B. Vesper Growth Note B: $2,800,000, $65,000,000 cap, no discount. Both use the 18,400,000-share pre-money denominator; denominator does not change between notes.
A10: Option pool 10% vs 12% | B10: Source: ironclad_cap_table.csv counsel note shows 10% available pool; growth_equity_diligence_brief.txt requires 12% post-money at closing. Treatment: Cap Table Pro Forma uses 12% sponsor case (2,013,126.55 incremental shares); Option pool cases also shows the 10% alternate.
A11: Quorum pro-rata allocation | B11: Source: growth_equity_diligence_brief.txt Primary allocation. Treatment: Quorum Ventures purchases $8,750,000.00 (4,600,000/18,400,000 × $35,000,000); Hartwell Partners takes $26,250,000.00. Modeling convention pending executed subscription documents.
A12: Forecast and cross-checks | B12: Revenue Forecast: 26%/22%/18%/15%/12% growth and 20% FCF margin from growth_equity_diligence_brief.txt. DCF: 13%–15% WACC, 3% terminal growth. Multiples: 4.5x–6.0x NTM; 4.0x TTM downside; Sensitivity uses Assumptions peer-median 5.2x.
