Workbook

Sheet Assumptions
A1: Governing assumptions — SI WC reserve 2025-12-31
A2: Source: actuarial_funding_memo.txt (retention, factors, beginning reserve)
A4: parameter | B4: value | C4: notes
A5: per_occurrence_retention | B5: 350000 | C5: SI retention cap
A6: beginning_si_reserve_2024_12_31 | B6: 1842660.4 | C6: Audited opening balance
A7: ibnr_factor_ay2022 | B7: 0.04 | C7: Memo factor
A8: ibnr_factor_ay2023 | B8: 0.11 | C8: Memo factor
A9: ibnr_factor_ay2024 | B9: 0.28 | C9: Memo factor
A10: ibnr_factor_ay2025 | B10: 0.52 | C10: Memo factor — not superseded 0.40
A11: superseded_ay2025_factor | B11: 0.4 | C11: Do not apply
A12: closed_claim_exclude | B12: CLM-2024-0901 | C12: Case forced to zero per memo
A13: large_loss_claim | B13: CLM-2024-1187 | C13: Retention cap applies
A14: subrogation_claim | B14: CLM-2023-0442 | C14: No credit until cash received
A15: valuation_date | B15: 2025-12-31 | C15: Year-end

Sheet Case Inventory
A1: Self-insured case reserves at 2025-12-31 (retention-capped)
A2: Source values: pelliston_open_claims_triangle.xlsx Open Inventory. SI case = MIN(TPA case, Assumptions retention); closed claim forced to zero.
A4: claim_number | B4: accident_year | C4: claimant | D4: tpa_case_reserve | E4: si_case_reserve | F4: excess_above_retention | G4: oi_paid_to_date | H4: notes
A5: CLM-2022-0198 | B5: 2022 | C5: R. Kessler | D5: 18400 | E5: =IF(A5=Assumptions!$B$12,0,MIN(D5,Assumptions!$B$5)) -> 18400 | F5: =IF(A5=Assumptions!$B$12,0,MAX(0,D5-E5)) -> 0 | G5: 23751.13
A6: CLM-2022-0311 | B6: 2022 | C6: J. Okonkwo | D6: 8220.4 | E6: =IF(A6=Assumptions!$B$12,0,MIN(D6,Assumptions!$B$5)) -> 8220.4 | F6: =IF(A6=Assumptions!$B$12,0,MAX(0,D6-E6)) -> 0 | G6: 29320.22
A7: CLM-2022-0402 | B7: 2022 | C7: P. Nanda | D7: 4110.18 | E7: =IF(A7=Assumptions!$B$12,0,MIN(D7,Assumptions!$B$5)) -> 4110.18 | F7: =IF(A7=Assumptions!$B$12,0,MAX(0,D7-E7)) -> 0 | G7: 6330.58
A8: CLM-2023-0088 | B8: 2023 | C8: A. Nguyen | D8: 22640.55 | E8: =IF(A8=Assumptions!$B$12,0,MIN(D8,Assumptions!$B$5)) -> 22640.55 | F8: =IF(A8=Assumptions!$B$12,0,MAX(0,D8-E8)) -> 0 | G8: 46630.77
A9: CLM-2023-0275 | B9: 2023 | C9: S. Patel | D9: 31200.18 | E9: =IF(A9=Assumptions!$B$12,0,MIN(D9,Assumptions!$B$5)) -> 31200.18 | F9: =IF(A9=Assumptions!$B$12,0,MAX(0,D9-E9)) -> 0 | G9: 51721.13
A10: CLM-2023-0442 | B10: 2023 | C10: M. Ortega | D10: 41200 | E10: =IF(A10=Assumptions!$B$12,0,MIN(D10,Assumptions!$B$5)) -> 41200 | F10: =IF(A10=Assumptions!$B$12,0,MAX(0,D10-E10)) -> 0 | G10: 53500.58 | H10: Expected subrogation not credited (cash not received)
A11: CLM-2023-0510 | B11: 2023 | C11: E. Soto | D11: 12880.4 | E11: =IF(A11=Assumptions!$B$12,0,MIN(D11,Assumptions!$B$5)) -> 12880.4 | F11: =IF(A11=Assumptions!$B$12,0,MAX(0,D11-E11)) -> 0 | G11: 10060.37
A12: CLM-2024-0044 | B12: 2024 | C12: L. Briggs | D12: 48220.18 | E12: =IF(A12=Assumptions!$B$12,0,MIN(D12,Assumptions!$B$5)) -> 48220.18 | F12: =IF(A12=Assumptions!$B$12,0,MAX(0,D12-E12)) -> 0 | G12: 60431.35
A13: CLM-2024-0612 | B13: 2024 | C13: K. Chen | D13: 27640.55 | E13: =IF(A13=Assumptions!$B$12,0,MIN(D13,Assumptions!$B$5)) -> 27640.55 | F13: =IF(A13=Assumptions!$B$12,0,MAX(0,D13-E13)) -> 0 | G13: 31510.58
A14: CLM-2024-1187 | B14: 2024 | C14: D. Vasquez | D14: 412800 | E14: =IF(A14=Assumptions!$B$12,0,MIN(D14,Assumptions!$B$5)) -> 350000 | F14: =IF(A14=Assumptions!$B$12,0,MAX(0,D14-E14)) -> 62800 | G14: 88420.18 | H14: TPA case capped at SI retention via Assumptions
A15: CLM-2024-0777 | B15: 2024 | C15: B. Mooney | D15: 19420.18 | E15: =IF(A15=Assumptions!$B$12,0,MIN(D15,Assumptions!$B$5)) -> 19420.18 | F15: =IF(A15=Assumptions!$B$12,0,MAX(0,D15-E15)) -> 0 | G15: 16631.13
A16: CLM-2024-0901 | B16: 2024 | C16: C. Delgado | D16: 6400 | E16: =IF(A16=Assumptions!$B$12,0,MIN(D16,Assumptions!$B$5)) -> 0 | F16: =IF(A16=Assumptions!$B$12,0,MAX(0,D16-E16)) -> 0 | G16: 18220.4 | H16: Removed — ledger final payment 2025-12-18; closed
A17: CLM-2025-0012 | B17: 2025 | C17: T. Quinn | D17: 34880.22 | E17: =IF(A17=Assumptions!$B$12,0,MIN(D17,Assumptions!$B$5)) -> 34880.22 | F17: =IF(A17=Assumptions!$B$12,0,MAX(0,D17-E17)) -> 0 | G17: 19410.8
A18: CLM-2025-0188 | B18: 2025 | C18: N. Blake | D18: 28640.18 | E18: =IF(A18=Assumptions!$B$12,0,MIN(D18,Assumptions!$B$5)) -> 28640.18 | F18: =IF(A18=Assumptions!$B$12,0,MAX(0,D18-E18)) -> 0 | G18: 21860.73
A19: CLM-2025-0330 | B19: 2025 | C19: H. Park | D19: 22110.4 | E19: =IF(A19=Assumptions!$B$12,0,MIN(D19,Assumptions!$B$5)) -> 22110.4 | F19: =IF(A19=Assumptions!$B$12,0,MAX(0,D19-E19)) -> 0 | G19: 11730.55
A20: CLM-2025-0419 | B20: 2025 | C20: I. Mendel | D20: 41200.18 | E20: =IF(A20=Assumptions!$B$12,0,MIN(D20,Assumptions!$B$5)) -> 41200.18 | F20: =IF(A20=Assumptions!$B$12,0,MAX(0,D20-E20)) -> 0 | G20: 7220.18
A21: CLM-2025-0502 | B21: 2025 | C21: F. Noor | D21: 18420.55 | E21: =IF(A21=Assumptions!$B$12,0,MIN(D21,Assumptions!$B$5)) -> 18420.55 | F21: =IF(A21=Assumptions!$B$12,0,MAX(0,D21-E21)) -> 0 | G21: 5300.58
A22: CLM-2025-0555 | B22: 2025 | C22: G. Alvarez | D22: 15880.4 | E22: =IF(A22=Assumptions!$B$12,0,MIN(D22,Assumptions!$B$5)) -> 15880.4 | F22: =IF(A22=Assumptions!$B$12,0,MAX(0,D22-E22)) -> 0 | G22: 2640.22
C23: Totals | E23: =SUM(E5:E22) -> 745064.55 | F23: =SUM(F5:F22) -> 62800

Sheet IBNR by AY
A1: Accident-year IBNR — Triangle cumulative paid + SI case × memo factor
A2: Cumulative paid from AY Triangle (cumulative_paid_as_of_2025_12). SI case from Case Inventory via SUMIF. Factors from Assumptions / actuarial_funding_memo.txt.
A4: accident_year | B4: cumulative_paid_triangle | C4: si_case_reserve | D4: ibnr_base | E4: ibnr_factor | F4: ibnr | G4: paid_source
A5: 2022 | B5: 136220.55 | C5: =SUMIF('Case Inventory'!B$5:B$22,A5,'Case Inventory'!E$5:E$22) -> 30730.58 | D5: =B5+C5 -> 166951.13 | E5: =Assumptions!B7 -> 0.04 | F5: =ROUND(D5*E5,2) -> 6678.05 | G5: AY Triangle cumulative_paid_as_of_2025_12
A6: 2023 | B6: 172640.55 | C6: =SUMIF('Case Inventory'!B$5:B$22,A6,'Case Inventory'!E$5:E$22) -> 107921.13 | D6: =B6+C6 -> 280561.68 | E6: =Assumptions!B8 -> 0.11 | F6: =ROUND(D6*E6,2) -> 30861.78 | G6: AY Triangle cumulative_paid_as_of_2025_12
A7: 2024 | B7: 186420.18 | C7: =SUMIF('Case Inventory'!B$5:B$22,A7,'Case Inventory'!E$5:E$22) -> 445280.91 | D7: =B7+C7 -> 631701.09 | E7: =Assumptions!B9 -> 0.28 | F7: =ROUND(D7*E7,2) -> 176876.31 | G7: AY Triangle cumulative_paid_as_of_2025_12
A8: 2025 | B8: 68220.4 | C8: =SUMIF('Case Inventory'!B$5:B$22,A8,'Case Inventory'!E$5:E$22) -> 161131.93 | D8: =B8+C8 -> 229352.33 | E8: =Assumptions!B10 -> 0.52 | F8: =ROUND(D8*E8,2) -> 119263.21 | G8: AY Triangle cumulative_paid_as_of_2025_12
A9: Total IBNR | F9: =SUM(F5:F8) -> 333679.35
A11: Superseded factor not used | B11: =Assumptions!B11 -> 0.4 | C11: Mid-year 2025 exhibit — do not apply

Sheet Excess Bridge
A1: Excess / ceded recoverable (not SI liability)
A2: Gross TPA case vs Assumptions retention; excess = gross − retention amount
A4: claim_number | B4: gross_tpa_case | C4: retention_amount | D4: si_case_capped | E4: excess_ceded_recoverable | F4: rule
A5: CLM-2024-1187 | B5: ='Case Inventory'!D14 -> 412800 | C5: =Assumptions!$B$5 -> 350000 | D5: =MIN(B5,C5) -> 350000 | E5: =MAX(0,B5-C5) -> 62800 | F5: actuarial_funding_memo.txt — SI retention; not SI liability

Sheet Reserve Rollforward
A1: Self-insured WC reserve rollforward to 2025-12-31
A3: line | B3: amount | C3: source
A4: Beginning SI reserve (2024-12-31) | B4: =Assumptions!B6 -> 1842660.4 | C4: Assumptions / actuarial_funding_memo.txt
A5: Net paid (calendar 2025, voids netted) | B5: 600226.54 | C5: pelliston_claims_payment_ledger.csv
A6: Net incurred (plug) | B6: =ROUND(B8+B5-B4,2) -> -163689.96 | C6: Identity: ending − beginning + paid
A7: SI case reserves (capped) | B7: ='Case Inventory'!E23 -> 745064.55 | C7: Case Inventory total
A8: Ending SI reserve (case + IBNR) | B8: =ROUND(B7+'IBNR by AY'!F9,2) -> 1078743.9 | C8: Case Inventory + IBNR by AY

Sheet Notes
A1: Methodology and source conflicts
A3: topic | B3: documentation
A4: IBNR paid source | B4: actuarial_funding_memo.txt requires IBNR on cumulative paid_to_date + SI case. Cumulative paid is taken from pelliston_open_claims_triangle.xlsx AY Triangle (cumulative_paid_as_of_2025_12), which covers the full accident-year population including closed claims. SI case comes from Open Inventory after retention caps.
A5: Mature years AY2022 / AY2023 | B5: Open Inventory open-claim paid sums ($59,401.93 / $161,912.85) are below Triangle cumulative paid ($136,220.55 / $172,640.55). Using only Open Inventory paid would understate the IBNR base on mature years. Triangle is the selected AY-level paid source.
A6: AY2024 paid conflict | B6: Open Inventory open-claim paid excluding CLM-2024-0901 = $196,993.24. AY Triangle cumulative_paid_as_of_2025_12 for AY2024 = $186,420.18. Open-subset paid exceeds AY-level cumulative by $10,573.06. If both were literal cumulative figures for the same population, an open subset cannot exceed the AY total — the sources cannot both be correct as stated. No bridge is provided in the source workbook. Selected source for IBNR: AY Triangle ($186,420.18). Effect: IBNR base uses Triangle paid + retention-capped SI case; Open Inventory paid is not used in the IBNR base for AY2024.
A7: Sources cited | B7: actuarial_funding_memo.txt; pelliston_open_claims_triangle.xlsx (AY Triangle and Open Inventory); pelliston_claims_payment_ledger.csv (calendar net paid).
A8: Memo treatments applied | B8: CLM-2024-1187 capped at retention; CLM-2024-0901 case zeroed; CLM-2023-0442 subrogation not credited; void pair excluded from net paid; AY2025 factor 0.52 (not 0.40).

Sheet Controller Recommendation
A1: Controller recommendation — SI WC reserve for audit / bank pack
A3: Ending SI liability to book | B3: ='Reserve Rollforward'!B8 -> 1078743.9
A4: Excess / ceded recoverable (disclosure) | B4: ='Excess Bridge'!E5 -> 62800
A5: Narrative
A6: Book self-insured workers compensation liability equal to the ending reserve on Reserve Rollforward (SI case from Case Inventory plus IBNR from IBNR by AY). Cap CLM-2024-1187 at the Assumptions retention per actuarial_funding_memo.txt and disclose Excess Bridge recoverable as excess-carrier recoverable, not SI liability. Do not credit expected subrogation on CLM-2023-0442 until cash is received. Apply AY2025 IBNR factor from Assumptions (0.52), not the superseded 0.40. Remove CLM-2024-0901 from case inventory per December ledger closure. AY IBNR uses Triangle cumulative paid; see Notes for the AY2024 Open Inventory vs Triangle paid conflict.
A12: Prohibited treatments not used
A13: Did not credit unpaid subrogation; did not carry uncapped TPA case on the large loss as SI liability; did not apply the mid-year 0.40 factor to AY2025; did not hide the AY2024 paid conflict between Open Inventory and AY Triangle.
